odoo/addons/pos_session_pay_invoice/README.rst
odoo/addons/pos_session_pay_invoice/__init__.py
odoo/addons/pos_session_pay_invoice/__manifest__.py
odoo/addons/pos_session_pay_invoice/i18n/es.po
odoo/addons/pos_session_pay_invoice/i18n/fr.po
odoo/addons/pos_session_pay_invoice/i18n/it.po
odoo/addons/pos_session_pay_invoice/i18n/pos_session_pay_invoice.pot
odoo/addons/pos_session_pay_invoice/models/__init__.py
odoo/addons/pos_session_pay_invoice/models/pos_order.py
odoo/addons/pos_session_pay_invoice/readme/CONFIGURE.rst
odoo/addons/pos_session_pay_invoice/readme/CONTRIBUTORS.rst
odoo/addons/pos_session_pay_invoice/readme/DESCRIPTION.rst
odoo/addons/pos_session_pay_invoice/readme/ROADMAP.rst
odoo/addons/pos_session_pay_invoice/readme/USAGE.rst
odoo/addons/pos_session_pay_invoice/security/ir.model.access.csv
odoo/addons/pos_session_pay_invoice/static/description/icon.png
odoo/addons/pos_session_pay_invoice/static/description/index.html
odoo/addons/pos_session_pay_invoice/tests/__init__.py
odoo/addons/pos_session_pay_invoice/tests/test_pay_invoice.py
odoo/addons/pos_session_pay_invoice/views/pos_session.xml
odoo/addons/pos_session_pay_invoice/wizard/__init__.py
odoo/addons/pos_session_pay_invoice/wizard/cash_invoice_in.py
odoo/addons/pos_session_pay_invoice/wizard/cash_invoice_in.xml
odoo/addons/pos_session_pay_invoice/wizard/pos_box_cash_invoice_in.py
odoo/addons/pos_session_pay_invoice/wizard/pos_box_cash_invoice_in.xml
odoo/addons/pos_session_pay_invoice/wizard/pos_box_cash_invoice_out.py
odoo/addons/pos_session_pay_invoice/wizard/pos_box_cash_invoice_out.xml
odoo14_addon_pos_session_pay_invoice-14.0.1.1.0.dist-info/METADATA
odoo14_addon_pos_session_pay_invoice-14.0.1.1.0.dist-info/WHEEL
odoo14_addon_pos_session_pay_invoice-14.0.1.1.0.dist-info/top_level.txt
odoo14_addon_pos_session_pay_invoice-14.0.1.1.0.dist-info/RECORD
